<?xml version="1.0" encoding="UTF-8"?><record_update>
    <sys_choice action="INSERT_OR_UPDATE" field="u_filter_menu_header" table="x_153465_discovert_tasker_filters" version="3">
        <sys_choice_set action="INSERT_OR_UPDATE">
            <element>u_filter_menu_header</element>
            <name>x_153465_discovert_tasker_filters</name>
            <sys_class_name>sys_choice_set</sys_class_name>
            <sys_created_by>jnadeem</sys_created_by>
            <sys_created_on>2021-11-29 23:45:42</sys_created_on>
            <sys_id>a0ba70c5dbfdc1501e1792c5d49619e8</sys_id>
            <sys_mod_count>0</sys_mod_count>
            <sys_name>u_filter_menu_header</sys_name>
            <sys_package display_value="Tasker" source="x_153465_discovert">c6b1162d4fc10300303dc3818110c7b1</sys_package>
            <sys_policy/>
            <sys_scope display_value="Tasker">c6b1162d4fc10300303dc3818110c7b1</sys_scope>
            <sys_update_name>sys_choice_x_153465_discovert_tasker_filters_u_filter_menu_header</sys_update_name>
            <sys_updated_by>jnadeem</sys_updated_by>
            <sys_updated_on>2021-11-29 23:45:42</sys_updated_on>
        </sys_choice_set>
        <sys_choice action="INSERT_OR_UPDATE">
            <dependent_value/>
            <element>u_filter_menu_header</element>
            <hint/>
            <inactive>false</inactive>
            <label>TASKS BY ME</label>
            <language>en</language>
            <name>x_153465_discovert_tasker_filters</name>
            <sequence>100</sequence>
            <synonyms/>
            <sys_created_by>jnadeem</sys_created_by>
            <sys_created_on>2021-11-29 23:45:42</sys_created_on>
            <sys_domain>global</sys_domain>
            <sys_domain_path>/</sys_domain_path>
            <sys_id>86dd0ff2db8c0510d0966ac2ca961993</sys_id>
            <sys_mod_count>3</sys_mod_count>
            <sys_updated_by>rjoy</sys_updated_by>
            <sys_updated_on>2022-07-14 19:49:32</sys_updated_on>
            <value>TASKS BY ME</value>
        </sys_choice>
        <sys_choice action="INSERT_OR_UPDATE">
            <dependent_value/>
            <element>u_filter_menu_header</element>
            <hint/>
            <inactive>false</inactive>
            <label>DRAFT TASKS</label>
            <language>en</language>
            <name>x_153465_discovert_tasker_filters</name>
            <sequence>200</sequence>
            <synonyms/>
            <sys_created_by>jnadeem</sys_created_by>
            <sys_created_on>2021-11-29 23:45:42</sys_created_on>
            <sys_domain>global</sys_domain>
            <sys_domain_path>/</sys_domain_path>
            <sys_id>42dd0ff2db8c0510d0966ac2ca961995</sys_id>
            <sys_mod_count>1</sys_mod_count>
            <sys_updated_by>rjoy</sys_updated_by>
            <sys_updated_on>2022-05-24 23:22:09</sys_updated_on>
            <value>DRAFT TASKS</value>
        </sys_choice>
        <sys_choice action="INSERT_OR_UPDATE">
            <dependent_value/>
            <element>u_filter_menu_header</element>
            <hint/>
            <inactive>false</inactive>
            <label>MY OPEN TASKS</label>
            <language>en</language>
            <name>x_153465_discovert_tasker_filters</name>
            <sequence>300</sequence>
            <synonyms/>
            <sys_created_by>jnadeem</sys_created_by>
            <sys_created_on>2021-11-29 23:45:42</sys_created_on>
            <sys_domain>global</sys_domain>
            <sys_domain_path>/</sys_domain_path>
            <sys_id>4add0ff2db8c0510d0966ac2ca961996</sys_id>
            <sys_mod_count>3</sys_mod_count>
            <sys_updated_by>rjoy</sys_updated_by>
            <sys_updated_on>2022-06-03 03:51:21</sys_updated_on>
            <value>MY OPEN TASKS</value>
        </sys_choice>
        <sys_choice action="INSERT_OR_UPDATE">
            <dependent_value/>
            <element>u_filter_menu_header</element>
            <hint/>
            <inactive>false</inactive>
            <label>MY CLOSED TASKS</label>
            <language>en</language>
            <name>x_153465_discovert_tasker_filters</name>
            <sequence>400</sequence>
            <synonyms/>
            <sys_created_by>jnadeem</sys_created_by>
            <sys_created_on>2021-11-29 23:45:42</sys_created_on>
            <sys_domain>global</sys_domain>
            <sys_domain_path>/</sys_domain_path>
            <sys_id>42dd0ff2db8c0510d0966ac2ca961998</sys_id>
            <sys_mod_count>1</sys_mod_count>
            <sys_updated_by>rjoy</sys_updated_by>
            <sys_updated_on>2022-05-24 23:22:17</sys_updated_on>
            <value>MY CLOSED TASKS</value>
        </sys_choice>
        <sys_choice action="INSERT_OR_UPDATE">
            <dependent_value/>
            <element>u_filter_menu_header</element>
            <hint/>
            <inactive>false</inactive>
            <label>TASK REQUESTS</label>
            <language>en</language>
            <name>x_153465_discovert_tasker_filters</name>
            <sequence>500</sequence>
            <synonyms/>
            <sys_created_by>jnadeem</sys_created_by>
            <sys_created_on>2021-11-29 23:45:42</sys_created_on>
            <sys_domain>global</sys_domain>
            <sys_domain_path>/</sys_domain_path>
            <sys_id>42dd0ff2db8c0510d0966ac2ca96199b</sys_id>
            <sys_mod_count>2</sys_mod_count>
            <sys_updated_by>rjoy</sys_updated_by>
            <sys_updated_on>2022-05-24 23:22:20</sys_updated_on>
            <value>TASK REQUESTS</value>
        </sys_choice>
        <sys_choice action="INSERT_OR_UPDATE">
            <dependent_value/>
            <element>u_filter_menu_header</element>
            <hint/>
            <inactive>false</inactive>
            <label>ORGANIZATIONAL REQUESTS</label>
            <language>en</language>
            <name>x_153465_discovert_tasker_filters</name>
            <sequence>600</sequence>
            <synonyms/>
            <sys_created_by>rjoy</sys_created_by>
            <sys_created_on>2022-05-25 00:20:11</sys_created_on>
            <sys_domain>global</sys_domain>
            <sys_domain_path>/</sys_domain_path>
            <sys_id>c78d696bdba701901e1792c5d496198c</sys_id>
            <sys_mod_count>0</sys_mod_count>
            <sys_updated_by>rjoy</sys_updated_by>
            <sys_updated_on>2022-05-25 00:20:11</sys_updated_on>
            <value>ORGANIZATIONAL REQUESTS</value>
        </sys_choice>
        <sys_choice action="INSERT_OR_UPDATE">
            <dependent_value/>
            <element>u_filter_menu_header</element>
            <hint/>
            <inactive>false</inactive>
            <label>MY SCHEDULED TASKS</label>
            <language>en</language>
            <name>x_153465_discovert_tasker_filters</name>
            <sequence>700</sequence>
            <synonyms/>
            <sys_created_by>jnadeem</sys_created_by>
            <sys_created_on>2021-11-29 23:45:42</sys_created_on>
            <sys_domain>global</sys_domain>
            <sys_domain_path>/</sys_domain_path>
            <sys_id>42dd0ff2db8c0510d0966ac2ca96199e</sys_id>
            <sys_mod_count>3</sys_mod_count>
            <sys_updated_by>rjoy</sys_updated_by>
            <sys_updated_on>2022-05-25 00:20:25</sys_updated_on>
            <value>MY SCHEDULED TASKS</value>
        </sys_choice>
        <sys_choice action="INSERT_OR_UPDATE">
            <dependent_value/>
            <element>u_filter_menu_header</element>
            <hint/>
            <inactive>false</inactive>
            <label>TASKS BY MY OU</label>
            <language>en</language>
            <name>x_153465_discovert_tasker_filters</name>
            <sequence>800</sequence>
            <synonyms/>
            <sys_created_by>rjoy</sys_created_by>
            <sys_created_on>2022-05-24 23:17:13</sys_created_on>
            <sys_domain>global</sys_domain>
            <sys_domain_path>/</sys_domain_path>
            <sys_id>782f55efdb6701901e1792c5d49619a7</sys_id>
            <sys_mod_count>7</sys_mod_count>
            <sys_updated_by>rjoy</sys_updated_by>
            <sys_updated_on>2022-07-14 19:55:03</sys_updated_on>
            <value>TASKS BY MY OU</value>
        </sys_choice>
        <sys_choice action="INSERT_OR_UPDATE">
            <dependent_value/>
            <element>u_filter_menu_header</element>
            <hint/>
            <inactive>false</inactive>
            <label>MY OU's OPEN TASKS</label>
            <language>en</language>
            <name>x_153465_discovert_tasker_filters</name>
            <sequence>900</sequence>
            <synonyms/>
            <sys_created_by>jnadeem</sys_created_by>
            <sys_created_on>2021-11-29 23:45:42</sys_created_on>
            <sys_domain>global</sys_domain>
            <sys_domain_path>/</sys_domain_path>
            <sys_id>4add0ff2db8c0510d0966ac2ca961999</sys_id>
            <sys_mod_count>8</sys_mod_count>
            <sys_updated_by>rjoy</sys_updated_by>
            <sys_updated_on>2022-07-18 15:16:04</sys_updated_on>
            <value>MY OU's OPEN TASKS</value>
        </sys_choice>
        <sys_choice action="INSERT_OR_UPDATE">
            <dependent_value/>
            <element>u_filter_menu_header</element>
            <hint/>
            <inactive>false</inactive>
            <label>MY OU'S CLOSED TASKS</label>
            <language>en</language>
            <name>x_153465_discovert_tasker_filters</name>
            <sequence>1000</sequence>
            <synonyms/>
            <sys_created_by>rjoy</sys_created_by>
            <sys_created_on>2022-05-24 23:07:28</sys_created_on>
            <sys_domain>global</sys_domain>
            <sys_domain_path>/</sys_domain_path>
            <sys_id>31ec9d6fdb6701901e1792c5d496196e</sys_id>
            <sys_mod_count>4</sys_mod_count>
            <sys_updated_by>rjoy</sys_updated_by>
            <sys_updated_on>2022-05-25 00:20:37</sys_updated_on>
            <value>MY OU'S CLOSED TASKS</value>
        </sys_choice>
        <sys_choice action="INSERT_OR_UPDATE">
            <dependent_value/>
            <element>u_filter_menu_header</element>
            <hint/>
            <inactive>false</inactive>
            <label>MY OU'S TASK REQUESTS</label>
            <language>en</language>
            <name>x_153465_discovert_tasker_filters</name>
            <sequence>1100</sequence>
            <synonyms/>
            <sys_created_by>rjoy</sys_created_by>
            <sys_created_on>2022-05-24 23:19:14</sys_created_on>
            <sys_domain>global</sys_domain>
            <sys_domain_path>/</sys_domain_path>
            <sys_id>4e9f55efdb6701901e1792c5d4961985</sys_id>
            <sys_mod_count>2</sys_mod_count>
            <sys_updated_by>rjoy</sys_updated_by>
            <sys_updated_on>2022-05-25 00:20:40</sys_updated_on>
            <value>MY OU'S TASK REQUESTS</value>
        </sys_choice>
        <sys_choice action="INSERT_OR_UPDATE">
            <dependent_value/>
            <element>u_filter_menu_header</element>
            <hint/>
            <inactive>false</inactive>
            <label>MY OU'S ORGANIZATIONAL REQUESTS</label>
            <language>en</language>
            <name>x_153465_discovert_tasker_filters</name>
            <sequence>1200</sequence>
            <synonyms/>
            <sys_created_by>jnadeem</sys_created_by>
            <sys_created_on>2021-11-29 23:45:42</sys_created_on>
            <sys_domain>global</sys_domain>
            <sys_domain_path>/</sys_domain_path>
            <sys_id>4add0ff2db8c0510d0966ac2ca96199c</sys_id>
            <sys_mod_count>5</sys_mod_count>
            <sys_updated_by>rjoy</sys_updated_by>
            <sys_updated_on>2022-05-25 00:20:43</sys_updated_on>
            <value>MY OU'S ORGANIZATIONAL REQUESTS</value>
        </sys_choice>
        <sys_choice action="INSERT_OR_UPDATE">
            <dependent_value/>
            <element>u_filter_menu_header</element>
            <hint/>
            <inactive>false</inactive>
            <label>MY OU'S SCHEDULE TASKS</label>
            <language>en</language>
            <name>x_153465_discovert_tasker_filters</name>
            <sequence>1300</sequence>
            <synonyms/>
            <sys_created_by>rjoy</sys_created_by>
            <sys_created_on>2022-05-24 23:09:57</sys_created_on>
            <sys_domain>global</sys_domain>
            <sys_domain_path>/</sys_domain_path>
            <sys_id>467d59afdb6701901e1792c5d496192e</sys_id>
            <sys_mod_count>5</sys_mod_count>
            <sys_updated_by>rjoy</sys_updated_by>
            <sys_updated_on>2022-05-25 00:20:46</sys_updated_on>
            <value>MY OU'S SCHEDULE TASKS</value>
        </sys_choice>
        <sys_choice action="INSERT_OR_UPDATE">
            <dependent_value/>
            <element>u_filter_menu_header</element>
            <hint/>
            <inactive>false</inactive>
            <label>Banner - My Tasks</label>
            <language>en</language>
            <name>x_153465_discovert_tasker_filters</name>
            <sequence>1400</sequence>
            <synonyms/>
            <sys_created_by>rjoy</sys_created_by>
            <sys_created_on>2022-06-04 20:33:02</sys_created_on>
            <sys_domain>global</sys_domain>
            <sys_domain_path>/</sys_domain_path>
            <sys_id>c4f22183dbb70dd0991a6154ca96195d</sys_id>
            <sys_mod_count>3</sys_mod_count>
            <sys_updated_by>rjoy</sys_updated_by>
            <sys_updated_on>2022-06-05 17:53:13</sys_updated_on>
            <value>banner_my_tasks</value>
        </sys_choice>
        <sys_choice action="INSERT_OR_UPDATE">
            <dependent_value/>
            <element>u_filter_menu_header</element>
            <hint/>
            <inactive>false</inactive>
            <label>Banner - Task Manager</label>
            <language>en</language>
            <name>x_153465_discovert_tasker_filters</name>
            <sequence>1500</sequence>
            <synonyms/>
            <sys_created_by>rjoy</sys_created_by>
            <sys_created_on>2022-06-05 17:22:35</sys_created_on>
            <sys_domain>global</sys_domain>
            <sys_domain_path>/</sys_domain_path>
            <sys_id>3201c6dbdb3f49901e1792c5d4961954</sys_id>
            <sys_mod_count>4</sys_mod_count>
            <sys_updated_by>rjoy</sys_updated_by>
            <sys_updated_on>2022-06-19 20:56:51</sys_updated_on>
            <value>banner_office_task_management</value>
        </sys_choice>
        <sys_choice action="INSERT_OR_UPDATE">
            <dependent_value/>
            <element>u_filter_menu_header</element>
            <hint/>
            <inactive>false</inactive>
            <label>Banner - Task Administrator</label>
            <language>en</language>
            <name>x_153465_discovert_tasker_filters</name>
            <sequence>1600</sequence>
            <synonyms/>
            <sys_created_by>rjoy</sys_created_by>
            <sys_created_on>2022-06-05 17:52:02</sys_created_on>
            <sys_domain>global</sys_domain>
            <sys_domain_path>/</sys_domain_path>
            <sys_id>52c70edfdb3f49901e1792c5d496197f</sys_id>
            <sys_mod_count>2</sys_mod_count>
            <sys_updated_by>rjoy</sys_updated_by>
            <sys_updated_on>2022-06-19 20:56:15</sys_updated_on>
            <value>banner_organizational_task_management</value>
        </sys_choice>
        <sys_choice action="INSERT_OR_UPDATE">
            <dependent_value/>
            <element>u_filter_menu_header</element>
            <hint/>
            <inactive>false</inactive>
            <label>Banner - Task Requests</label>
            <language>en</language>
            <name>x_153465_discovert_tasker_filters</name>
            <sequence>1600</sequence>
            <synonyms/>
            <sys_created_by>rjoy</sys_created_by>
            <sys_created_on>2022-06-05 18:26:20</sys_created_on>
            <sys_domain>global</sys_domain>
            <sys_domain_path>/</sys_domain_path>
            <sys_id>30af8e57db7f49901e1792c5d49619fc</sys_id>
            <sys_mod_count>0</sys_mod_count>
            <sys_updated_by>rjoy</sys_updated_by>
            <sys_updated_on>2022-06-05 18:26:20</sys_updated_on>
            <value>banner_task_requests</value>
        </sys_choice>
        <sys_choice action="INSERT_OR_UPDATE">
            <dependent_value/>
            <element>u_filter_menu_header</element>
            <hint/>
            <inactive>false</inactive>
            <label>Banner - Hierarchy Requests</label>
            <language>en</language>
            <name>x_153465_discovert_tasker_filters</name>
            <sequence>1700</sequence>
            <synonyms/>
            <sys_created_by>rjoy</sys_created_by>
            <sys_created_on>2022-06-05 18:53:07</sys_created_on>
            <sys_domain>global</sys_domain>
            <sys_domain_path>/</sys_domain_path>
            <sys_id>41c5d29bdb7f49901e1792c5d496199f</sys_id>
            <sys_mod_count>1</sys_mod_count>
            <sys_updated_by>rjoy</sys_updated_by>
            <sys_updated_on>2022-06-19 20:57:09</sys_updated_on>
            <value>banner_organizational_hierarchy_requests</value>
        </sys_choice>
    </sys_choice>
</record_update>
