<?xml version="1.0" encoding="UTF-8"?><record_update table="sp_css_include">
    <sp_css_include action="INSERT_OR_UPDATE">
        <name>Tasker UINotificationContainerCSSInclude</name>
        <source>local</source>
        <sp_css display_value="Tasker UI Notification Container Style Sheet">1e02a6d11b4eb410888aebde6e4bcb5a</sp_css>
        <sys_class_name>sp_css_include</sys_class_name>
        <sys_created_by>mmccune</sys_created_by>
        <sys_created_on>2021-08-17 18:41:26</sys_created_on>
        <sys_customer_update>false</sys_customer_update>
        <sys_id>a8916a911b4eb410888aebde6e4bcbbe</sys_id>
        <sys_mod_count>1</sys_mod_count>
        <sys_name>Tasker UINotificationContainerCSSInclude</sys_name>
        <sys_package display_value="Tasker" source="x_153465_discovert">c6b1162d4fc10300303dc3818110c7b1</sys_package>
        <sys_policy/>
        <sys_replace_on_upgrade>false</sys_replace_on_upgrade>
        <sys_scope display_value="Tasker">c6b1162d4fc10300303dc3818110c7b1</sys_scope>
        <sys_update_name>sp_css_include_a8916a911b4eb410888aebde6e4bcbbe</sys_update_name>
        <sys_updated_by>mmccune</sys_updated_by>
        <sys_updated_on>2021-08-17 18:42:31</sys_updated_on>
        <url/>
    </sp_css_include>
</record_update>
