<?xml version="1.0" encoding="UTF-8"?><record_update table="sp_instance_table">
    <sp_instance_table action="INSERT_OR_UPDATE">
        <active>true</active>
        <class_name/>
        <color>default</color>
        <css/>
        <display_field/>
        <field_list/>
        <filter/>
        <glyph/>
        <id/>
        <maximum_entries>10</maximum_entries>
        <order>10</order>
        <order_by/>
        <order_direction>asc</order_direction>
        <roles/>
        <short_description/>
        <size>md</size>
        <sp_column display_value="1">82e54848db8c6f00bb8ee536ca961974</sp_column>
        <sp_page/>
        <sp_widget display_value="Template List Tabbed">a86fe00a4fe89700303dc3818110c704</sp_widget>
        <sys_class_name>sp_instance_table</sys_class_name>
        <sys_created_by>admin</sys_created_by>
        <sys_created_on>2018-08-15 19:02:18</sys_created_on>
        <sys_id>9ff58c48db8c6f00bb8ee536ca9619a0</sys_id>
        <sys_mod_count>40</sys_mod_count>
        <sys_name>List</sys_name>
        <sys_package display_value="Tasker" source="x_153465_discovert">c6b1162d4fc10300303dc3818110c7b1</sys_package>
        <sys_policy>protected</sys_policy>
        <sys_scope display_value="Tasker">c6b1162d4fc10300303dc3818110c7b1</sys_scope>
        <sys_update_name>sp_instance_table_9ff58c48db8c6f00bb8ee536ca9619a0</sys_update_name>
        <sys_updated_by>rjoy</sys_updated_by>
        <sys_updated_on>2020-10-25 05:27:51</sys_updated_on>
        <table/>
        <title>List</title>
        <url/>
        <widget_parameters><![CDATA[{
	"link1": {
		"value": "?show_keywords=true&show_breadcrumbs=true&enable_filter=true&table=x_153465_discovert_discover_routing_template&role=x_153465_discovert.tasker_process_template_user&title=Personal Templates&filter=process_level=my_process^process_ownerDYNAMIC90d1921e5f510100a9ad2572f2b477fe&page=discovertasker_processtemplatelist&view=MyProcess&o=sys_updated_on&d=desc",
		"displayValue": "?show_keywords=true&show_breadcrumbs=true&enable_filter=true&table=x_153465_discovert_discover_routing_template&role=x_153465_discovert.tasker_process_template_user&title=Personal Templates&filter=process_level=my_process^process_ownerDYNAMIC90d1921e5f510100a9ad2572f2b477fe&page=discovertasker_processtemplatelist&view=MyProcess&o=sys_updated_on&d=desc"
	},
	"link2": {
		"value": "?show_keywords=true&show_breadcrumbs=true&enable_filter=true&table=x_153465_discovert_discover_routing_template&role=template_ou&title=OU Templates&filter=process_level=ou_process&page=discovertasker_processtemplatelist&view=OUProcess&o=sys_updated_on&d=desc",
		"displayValue": "?show_keywords=true&show_breadcrumbs=true&enable_filter=true&table=x_153465_discovert_discover_routing_template&role=template_ou&title=OU Templates&filter=process_level=ou_process&page=discovertasker_processtemplatelist&view=OUProcess&o=sys_updated_on&d=desc"
	},
	"link3": {
		"value": "?show_keywords=true&show_breadcrumbs=true&enable_filter=true&table=x_153465_discovert_discover_routing_template&role=x_153465_discovert.tasker_process_template_global&title=Global Templates&filter=process_level=global_process&page=discovertasker_processtemplatelist&view=GlobalProcess&o=sys_updated_on&d=desc",
		"displayValue": "?show_keywords=true&show_breadcrumbs=true&enable_filter=true&table=x_153465_discovert_discover_routing_template&role=x_153465_discovert.tasker_process_template_global&title=Global Templates&filter=process_level=global_process&page=discovertasker_processtemplatelist&view=GlobalProcess&o=sys_updated_on&d=desc"
	},
	"link4": {
		"value": "",
		"displayValue": ""
	},
	"link5": {
		"value": "",
		"displayValue": ""
	},
	"security_link1": {
		"value": "",
		"displayValue": ""
	}
}]]></widget_parameters>
    </sp_instance_table>
    <sys_translated_text action="delete_multiple" query="documentkey=9ff58c48db8c6f00bb8ee536ca9619a0"/>
</record_update>
